odoo/addons/ssi_stock_revaluation/README.rst
odoo/addons/ssi_stock_revaluation/__init__.py
odoo/addons/ssi_stock_revaluation/__manifest__.py
odoo/addons/ssi_stock_revaluation/menu.xml
odoo/addons/ssi_stock_revaluation/data/approval_template_data.xml
odoo/addons/ssi_stock_revaluation/data/ir_sequence_data.xml
odoo/addons/ssi_stock_revaluation/data/policy_template_data.xml
odoo/addons/ssi_stock_revaluation/data/sequence_template_data.xml
odoo/addons/ssi_stock_revaluation/models/__init__.py
odoo/addons/ssi_stock_revaluation/models/stock_revaluation.py
odoo/addons/ssi_stock_revaluation/models/stock_revaluation_type.py
odoo/addons/ssi_stock_revaluation/security/ir.model.access.csv
odoo/addons/ssi_stock_revaluation/security/ir_module_category_data.xml
odoo/addons/ssi_stock_revaluation/security/ir_rule_data.xml
odoo/addons/ssi_stock_revaluation/security/res_group_data.xml
odoo/addons/ssi_stock_revaluation/static/description/icon.png
odoo/addons/ssi_stock_revaluation/views/stock_revaluation_type_views.xml
odoo/addons/ssi_stock_revaluation/views/stock_revaluation_views.xml
odoo14_addon_ssi_stock_revaluation-14.0.1.2.0.dist-info/METADATA
odoo14_addon_ssi_stock_revaluation-14.0.1.2.0.dist-info/WHEEL
odoo14_addon_ssi_stock_revaluation-14.0.1.2.0.dist-info/top_level.txt
odoo14_addon_ssi_stock_revaluation-14.0.1.2.0.dist-info/RECORD
